ambivo_agents/__init__.py
ambivo_agents/cli.py
ambivo_agents/agents/__init__.py
ambivo_agents/agents/analytics.py
ambivo_agents/agents/api_agent.py
ambivo_agents/agents/assistant.py
ambivo_agents/agents/code_executor.py
ambivo_agents/agents/database_agent.py
ambivo_agents/agents/gather_agent.py
ambivo_agents/agents/knowledge_base.py
ambivo_agents/agents/knowledge_synthesis.py
ambivo_agents/agents/media_editor.py
ambivo_agents/agents/moderator.py
ambivo_agents/agents/response_quality_assessor.py
ambivo_agents/agents/web_scraper.py
ambivo_agents/agents/web_search.py
ambivo_agents/agents/workflow_developer.py
ambivo_agents/agents/youtube_download.py
ambivo_agents/config/__init__.py
ambivo_agents/config/loader.py
ambivo_agents/core/__init__.py
ambivo_agents/core/base.py
ambivo_agents/core/docker_shared.py
ambivo_agents/core/enhanced_workflow.py
ambivo_agents/core/file_resolution.py
ambivo_agents/core/history.py
ambivo_agents/core/interactive_workflow.py
ambivo_agents/core/llm.py
ambivo_agents/core/memory.py
ambivo_agents/core/workflow.py
ambivo_agents/core/workflow_orchestrator.py
ambivo_agents/core/persistence/__init__.py
ambivo_agents/core/persistence/sqlite_backend.py
ambivo_agents/executors/__init__.py
ambivo_agents/executors/docker_executor.py
ambivo_agents/executors/media_executor.py
ambivo_agents/executors/youtube_executor.py
ambivo_agents/services/__init__.py
ambivo_agents/services/agent_service.py
ambivo_agents/services/factory.py
ambivo_agents/services/file_processor.py
ambivo_agents/services/presentation_generator.py
ambivo_agents/services/python_code_formatter.py
ambivo_agents-1.4.0.dist-info/licenses/LICENSE
ambivo_agents-1.4.0.dist-info/METADATA
ambivo_agents-1.4.0.dist-info/WHEEL
ambivo_agents-1.4.0.dist-info/entry_points.txt
ambivo_agents-1.4.0.dist-info/top_level.txt
ambivo_agents-1.4.0.dist-info/RECORD
