Metadata-Version: 2.4
Name: ambivo-agents
Version: 1.4.0
Summary: Multi-Agent AI System for automation
Home-page: https://github.com/ambivo-corp/ambivo-agents
Author: Hemant Gosain 'Sunny'
Author-email: Hemant Gosain 'Sunny' <info@ambivo.com>
License: MIT
Project-URL: Homepage, https://github.com/ambivo-corp/ambivo-agents
Project-URL: Repository, https://github.com/ambivo-corp/ambivo-agents
Project-URL: Issues, https://github.com/ambivo-corp/ambivo-agents/issues
Project-URL: Documentation, https://github.com/ambivo-corp/ambivo-agents/blob/main/README.md
Project-URL: Company, https://www.ambivo.com
Classifier: Development Status :: 4 - Beta
Classifier: Intended Audience :: Developers
Classifier: License :: OSI Approved :: MIT License
Classifier: Operating System :: OS Independent
Classifier: Programming Language :: Python :: 3
Classifier: Programming Language :: Python :: 3.11
Classifier: Programming Language :: Python :: 3.12
Classifier: Programming Language :: Python :: 3.13
Classifier: Topic :: Software Development :: Libraries :: Python Modules
Classifier: Topic :: Scientific/Engineering :: Artificial Intelligence
Classifier: Topic :: Communications
Requires-Python: >=3.11
License-File: LICENSE
Requires-Dist: redis>=6.2.0
Requires-Dist: redis[asyncio]
Requires-Dist: docker>=6.0.0
Requires-Dist: asyncio-mqtt>=0.11.0
Requires-Dist: cachetools
Requires-Dist: lz4
Requires-Dist: requests>=2.32.4
Requires-Dist: click>=8.2.1
Requires-Dist: openai>=1.84.0
Requires-Dist: langchain>=0.3.25
Requires-Dist: langchain-community>=0.3.24
Requires-Dist: langchain-core>=0.3.63
Requires-Dist: langchain-openai>=0.3.19
Requires-Dist: langchainhub>=0.1.21
Requires-Dist: langchain-text-splitters>=0.3.8
Requires-Dist: langchain-anthropic>=0.3.15
Requires-Dist: langchain-aws
Requires-Dist: langchain-voyageai
Requires-Dist: huggingface-hub
Requires-Dist: llama-index-core
Requires-Dist: llama-index-embeddings-langchain
Requires-Dist: llama-index-llms-langchain
Requires-Dist: llama-index-llms-openai
Requires-Dist: llama-index-vector-stores-qdrant
Requires-Dist: llama-index-readers-smart-pdf-loader
Requires-Dist: pydantic>=2.11.7
Requires-Dist: boto3>=1.38.42
Requires-Dist: python-dotenv>=1.1.1
Requires-Dist: pyyaml>=6.0.2
Requires-Dist: psutil>=7.0.0
Requires-Dist: qdrant-client
Requires-Dist: numexpr
Requires-Dist: pytest>=8.4.1
Requires-Dist: pytest-asyncio>=1.0.0
Requires-Dist: black>=25.1.0
Requires-Dist: isort>=6.0.1
Requires-Dist: unstructured
Requires-Dist: langchain-unstructured
Provides-Extra: web
Requires-Dist: beautifulsoup4>=4.13.4; extra == "web"
Requires-Dist: playwright>=1.40.0; extra == "web"
Provides-Extra: media
Requires-Dist: pytubefix>=6.0.0; extra == "media"
Provides-Extra: anthropic
Requires-Dist: anthropic>=0.55.0; extra == "anthropic"
Provides-Extra: database
Requires-Dist: pymongo>=4.0.0; extra == "database"
Requires-Dist: mysql-connector-python>=8.0.0; extra == "database"
Requires-Dist: psycopg2-binary>=2.9.0; extra == "database"
Requires-Dist: tabulate>=0.9.0; extra == "database"
Provides-Extra: test
Requires-Dist: pytest>=8.4.1; extra == "test"
Requires-Dist: pytest-asyncio>=1.0.0; extra == "test"
Requires-Dist: pytest-timeout>=2.1.0; extra == "test"
Provides-Extra: dev
Requires-Dist: pytest>=8.4.1; extra == "dev"
Requires-Dist: pytest-asyncio>=1.0.0; extra == "dev"
Requires-Dist: black>=25.1.0; extra == "dev"
Requires-Dist: isort>=6.0.1; extra == "dev"
Requires-Dist: pytest-timeout>=2.1.0; extra == "dev"
Requires-Dist: pre-commit>=3.0.0; extra == "dev"
Provides-Extra: full
Requires-Dist: ambivo-agents[anthropic,database,media,web]; extra == "full"
Provides-Extra: all
Requires-Dist: pytest>=8.4.1; extra == "all"
Requires-Dist: pytest-asyncio>=1.0.0; extra == "all"
Requires-Dist: black>=25.1.0; extra == "all"
Requires-Dist: isort>=6.0.1; extra == "all"
Requires-Dist: pytest-timeout>=2.1.0; extra == "all"
Requires-Dist: beautifulsoup4>=4.13.4; extra == "all"
Requires-Dist: playwright>=1.40.0; extra == "all"
Requires-Dist: pytubefix>=6.0.0; extra == "all"
Requires-Dist: anthropic>=0.55.0; extra == "all"
Requires-Dist: pymongo>=4.0.0; extra == "all"
Requires-Dist: mysql-connector-python>=8.0.0; extra == "all"
Requires-Dist: psycopg2-binary>=2.9.0; extra == "all"
Requires-Dist: tabulate>=0.9.0; extra == "all"
Requires-Dist: pre-commit>=3.0.0; extra == "all"
Dynamic: author
Dynamic: home-page
Dynamic: license-file
Dynamic: requires-python
